{
  "generated_at": "2026-05-15T15:10:27.982Z",
  "status": "ok",
  "summary": {
    "latest_build_seconds": 747,
    "avg_build_seconds_7d": 745,
    "avg_build_seconds_30d": 754,
    "current_page_count": 1,
    "ms_per_page_latest": 747000,
    "flag_slow": true
  },
  "trend": [
    {
      "run_id": 25923792343,
      "started_at": "2026-05-15T14:39:13Z",
      "build_seconds": 747,
      "url": "https://github.com/frank890417/taiwan-md/actions/runs/25923792343/job/76199523515"
    },
    {
      "run_id": 25922564118,
      "started_at": "2026-05-15T14:13:47Z",
      "build_seconds": 751,
      "url": "https://github.com/frank890417/taiwan-md/actions/runs/25922564118/job/76195195906"
    },
    {
      "run_id": 25908845796,
      "started_at": "2026-05-15T08:45:44Z",
      "build_seconds": 758,
      "url": "https://github.com/frank890417/taiwan-md/actions/runs/25908845796/job/76148585276"
    },
    {
      "run_id": 25903900402,
      "started_at": "2026-05-15T06:28:22Z",
      "build_seconds": 751,
      "url": "https://github.com/frank890417/taiwan-md/actions/runs/25903900402/job/76133147689"
    },
    {
      "run_id": 25903009036,
      "started_at": "2026-05-15T06:00:54Z",
      "build_seconds": 739,
      "url": "https://github.com/frank890417/taiwan-md/actions/runs/25903009036/job/76130294859"
    },
    {
      "run_id": 25873536975,
      "started_at": "2026-05-14T17:00:34Z",
      "build_seconds": 730,
      "url": "https://github.com/frank890417/taiwan-md/actions/runs/25873536975/job/76034723211"
    },
    {
      "run_id": 25839284740,
      "started_at": "2026-05-14T03:07:43Z",
      "build_seconds": 739,
      "url": "https://github.com/frank890417/taiwan-md/actions/runs/25839284740/job/75920917959"
    },
    {
      "run_id": 25808157014,
      "started_at": "2026-05-13T15:14:29Z",
      "build_seconds": 775,
      "url": "https://github.com/frank890417/taiwan-md/actions/runs/25808157014/job/75816876712"
    },
    {
      "run_id": 25806334385,
      "started_at": "2026-05-13T14:41:45Z",
      "build_seconds": 739,
      "url": "https://github.com/frank890417/taiwan-md/actions/runs/25806334385/job/75810014495"
    },
    {
      "run_id": 25804460200,
      "started_at": "2026-05-13T14:09:09Z",
      "build_seconds": 811,
      "url": "https://github.com/frank890417/taiwan-md/actions/runs/25804460200/job/75803250030"
    }
  ]
}
